{
  "openapi": "3.0.1",
  "info": {
    "title": "NewsPaper API",
    "version": "v1"
  },
  "paths": {
    "/api/Category/GetCategories": {
      "get": {
        "tags": [
          "Category"
        ],
        "responses": {
          "200": {
            "description": "OK"
          }
        }
      }
    },
    "/api/Category/CreateCategory": {
      "post": {
        "tags": [
          "Category"
        ],
        "requestBody": {
          "content": {
            "application/json": {
              "schema": {
                "$ref": "#/components/schemas/CategoryDto"
              }
            },
            "text/json": {
              "schema": {
                "$ref": "#/components/schemas/CategoryDto"
              }
            },
            "application/*+json": {
              "schema": {
                "$ref": "#/components/schemas/CategoryDto"
              }
            }
          }
        },
        "responses": {
          "200": {
            "description": "OK",
            "content": {
              "text/plain": {
                "schema": {
                  "$ref": "#/components/schemas/ResponseData"
                }
              },
              "application/json": {
                "schema": {
                  "$ref": "#/components/schemas/ResponseData"
                }
              },
              "text/json": {
                "schema": {
                  "$ref": "#/components/schemas/ResponseData"
                }
              }
            }
          }
        }
      }
    },
    "/api/Category/UpdateCategory": {
      "put": {
        "tags": [
          "Category"
        ],
        "responses": {
          "200": {
            "description": "OK"
          }
        }
      }
    },
    "/api/Category/DeleteCategory": {
      "delete": {
        "tags": [
          "Category"
        ],
        "responses": {
          "200": {
            "description": "OK"
          }
        }
      }
    },
    "/api/ChildrenCategory/GetChildrenCategories": {
      "get": {
        "tags": [
          "ChildrenCategory"
        ],
        "responses": {
          "200": {
            "description": "OK"
          }
        }
      }
    },
    "/api/ChildrenCategory/CreateChildrenCategory": {
      "post": {
        "tags": [
          "ChildrenCategory"
        ],
        "responses": {
          "200": {
            "description": "OK"
          }
        }
      }
    },
    "/api/ChildrenCategory/UpdateChildrenCategory": {
      "put": {
        "tags": [
          "ChildrenCategory"
        ],
        "responses": {
          "200": {
            "description": "OK"
          }
        }
      }
    },
    "/api/ChildrenCategory/DeleteChildrenCategory": {
      "delete": {
        "tags": [
          "ChildrenCategory"
        ],
        "responses": {
          "200": {
            "description": "OK"
          }
        }
      }
    },
    "/api/Comment": {
      "get": {
        "tags": [
          "Comment"
        ],
        "responses": {
          "200": {
            "description": "OK"
          }
        }
      },
      "post": {
        "tags": [
          "Comment"
        ],
        "responses": {
          "200": {
            "description": "OK"
          }
        }
      },
      "put": {
        "tags": [
          "Comment"
        ],
        "responses": {
          "200": {
            "description": "OK"
          }
        }
      },
      "delete": {
        "tags": [
          "Comment"
        ],
        "responses": {
          "200": {
            "description": "OK"
          }
        }
      }
    },
    "/api/MediaFile": {
      "get": {
        "tags": [
          "MediaFile"
        ],
        "responses": {
          "200": {
            "description": "OK"
          }
        }
      },
      "post": {
        "tags": [
          "MediaFile"
        ],
        "responses": {
          "200": {
            "description": "OK"
          }
        }
      },
      "put": {
        "tags": [
          "MediaFile"
        ],
        "responses": {
          "200": {
            "description": "OK"
          }
        }
      },
      "delete": {
        "tags": [
          "MediaFile"
        ],
        "responses": {
          "200": {
            "description": "OK"
          }
        }
      }
    },
    "/api/News/GetNewsByIdAsync": {
      "get": {
        "tags": [
          "News"
        ],
        "parameters": [
          {
            "name": "id",
            "in": "query",
            "schema": {
              "type": "integer",
              "format": "int32"
            }
          }
        ],
        "responses": {
          "200": {
            "description": "OK",
            "content": {
              "text/plain": {
                "schema": {
                  "$ref": "#/components/schemas/NewsDto"
                }
              },
              "application/json": {
                "schema": {
                  "$ref": "#/components/schemas/NewsDto"
                }
              },
              "text/json": {
                "schema": {
                  "$ref": "#/components/schemas/NewsDto"
                }
              }
            }
          }
        }
      }
    },
    "/api/News/CreateNewPost": {
      "post": {
        "tags": [
          "News"
        ],
        "requestBody": {
          "content": {
            "multipart/form-data": {
              "schema": {
                "type": "object",
                "properties": {
                  "Header": {
                    "type": "string"
                  },
                  "Title": {
                    "type": "string"
                  },
                  "Content": {
                    "type": "string"
                  },
                  "Footer": {
                    "type": "string"
                  },
                  "Links": {
                    "type": "string"
                  },
                  "TimeReading": {
                    "type": "integer",
                    "format": "int32"
                  },
                  "UserId": {
                    "type": "integer",
                    "format": "int32"
                  },
                  "CategoryId": {
                    "type": "integer",
                    "format": "int32"
                  },
                  "ImagesId": {
                    "type": "integer",
                    "format": "int32"
                  }
                }
              },
              "encoding": {
                "Header": {
                  "style": "form"
                },
                "Title": {
                  "style": "form"
                },
                "Content": {
                  "style": "form"
                },
                "Footer": {
                  "style": "form"
                },
                "Links": {
                  "style": "form"
                },
                "TimeReading": {
                  "style": "form"
                },
                "UserId": {
                  "style": "form"
                },
                "CategoryId": {
                  "style": "form"
                },
                "ImagesId": {
                  "style": "form"
                }
              }
            }
          }
        },
        "responses": {
          "200": {
            "description": "OK"
          }
        }
      }
    },
    "/api/News": {
      "put": {
        "tags": [
          "News"
        ],
        "parameters": [
          {
            "name": "id",
            "in": "query",
            "schema": {
              "type": "integer",
              "format": "int32"
            }
          }
        ],
        "requestBody": {
          "content": {
            "application/json": {
              "schema": {
                "$ref": "#/components/schemas/NewsDto"
              }
            },
            "text/json": {
              "schema": {
                "$ref": "#/components/schemas/NewsDto"
              }
            },
            "application/*+json": {
              "schema": {
                "$ref": "#/components/schemas/NewsDto"
              }
            }
          }
        },
        "responses": {
          "200": {
            "description": "OK"
          }
        }
      }
    },
    "/api/News/{id}": {
      "delete": {
        "tags": [
          "News"
        ],
        "parameters": [
          {
            "name": "id",
            "in": "path",
            "required": true,
            "schema": {
              "type": "integer",
              "format": "int32"
            }
          }
        ],
        "responses": {
          "200": {
            "description": "OK"
          }
        }
      }
    },
    "/api/Saved/GetYourListSaved": {
      "get": {
        "tags": [
          "Saved"
        ],
        "responses": {
          "200": {
            "description": "OK"
          }
        }
      }
    },
    "/api/Saved/AddOrRemoveSaved": {
      "post": {
        "tags": [
          "Saved"
        ],
        "requestBody": {
          "content": {
            "application/json": {
              "schema": {
                "$ref": "#/components/schemas/SavedDto"
              }
            },
            "text/json": {
              "schema": {
                "$ref": "#/components/schemas/SavedDto"
              }
            },
            "application/*+json": {
              "schema": {
                "$ref": "#/components/schemas/SavedDto"
              }
            }
          }
        },
        "responses": {
          "200": {
            "description": "OK"
          }
        }
      }
    },
    "/api/User/UserLogin": {
      "post": {
        "tags": [
          "User"
        ],
        "requestBody": {
          "content": {
            "application/json": {
              "schema": {
                "$ref": "#/components/schemas/UserDto"
              }
            },
            "text/json": {
              "schema": {
                "$ref": "#/components/schemas/UserDto"
              }
            },
            "application/*+json": {
              "schema": {
                "$ref": "#/components/schemas/UserDto"
              }
            }
          }
        },
        "responses": {
          "200": {
            "description": "OK",
            "content": {
              "text/plain": {
                "schema": {
                  "$ref": "#/components/schemas/ResponseData"
                }
              },
              "application/json": {
                "schema": {
                  "$ref": "#/components/schemas/ResponseData"
                }
              },
              "text/json": {
                "schema": {
                  "$ref": "#/components/schemas/ResponseData"
                }
              }
            }
          }
        }
      }
    },
    "/api/User/UserRegister": {
      "post": {
        "tags": [
          "User"
        ],
        "requestBody": {
          "content": {
            "application/json": {
              "schema": {
                "$ref": "#/components/schemas/UserRegisterDto"
              }
            },
            "text/json": {
              "schema": {
                "$ref": "#/components/schemas/UserRegisterDto"
              }
            },
            "application/*+json": {
              "schema": {
                "$ref": "#/components/schemas/UserRegisterDto"
              }
            }
          }
        },
        "responses": {
          "200": {
            "description": "OK",
            "content": {
              "text/plain": {
                "schema": {
                  "$ref": "#/components/schemas/ResponseData"
                }
              },
              "application/json": {
                "schema": {
                  "$ref": "#/components/schemas/ResponseData"
                }
              },
              "text/json": {
                "schema": {
                  "$ref": "#/components/schemas/ResponseData"
                }
              }
            }
          }
        }
      }
    },
    "/api/User": {
      "post": {
        "tags": [
          "User"
        ],
        "requestBody": {
          "content": {
            "application/json": {
              "schema": {
                "$ref": "#/components/schemas/UserRegisterDto"
              }
            },
            "text/json": {
              "schema": {
                "$ref": "#/components/schemas/UserRegisterDto"
              }
            },
            "application/*+json": {
              "schema": {
                "$ref": "#/components/schemas/UserRegisterDto"
              }
            }
          }
        },
        "responses": {
          "200": {
            "description": "OK",
            "content": {
              "text/plain": {
                "schema": {
                  "$ref": "#/components/schemas/ResponseData"
                }
              },
              "application/json": {
                "schema": {
                  "$ref": "#/components/schemas/ResponseData"
                }
              },
              "text/json": {
                "schema": {
                  "$ref": "#/components/schemas/ResponseData"
                }
              }
            }
          }
        }
      },
      "delete": {
        "tags": [
          "User"
        ],
        "responses": {
          "200": {
            "description": "OK"
          }
        }
      }
    }
  },
  "components": {
    "schemas": {
      "CategoryDto": {
        "type": "object",
        "properties": {
          "categoryName": {
            "type": "string",
            "nullable": true
          }
        },
        "additionalProperties": false
      },
      "NewsDto": {
        "type": "object",
        "properties": {
          "header": {
            "type": "string",
            "nullable": true
          },
          "title": {
            "type": "string",
            "nullable": true
          },
          "content": {
            "type": "string",
            "nullable": true
          },
          "footer": {
            "type": "string",
            "nullable": true
          },
          "links": {
            "type": "string",
            "nullable": true
          },
          "timeReading": {
            "type": "integer",
            "format": "int32",
            "nullable": true
          },
          "userId": {
            "type": "integer",
            "format": "int32"
          },
          "categoryId": {
            "type": "integer",
            "format": "int32",
            "nullable": true
          },
          "imagesId": {
            "type": "integer",
            "format": "int32",
            "nullable": true
          }
        },
        "additionalProperties": false
      },
      "ResponseData": {
        "type": "object",
        "properties": {
          "data": {
            "nullable": true
          },
          "statusCode": {
            "type": "integer",
            "format": "int32"
          }
        },
        "additionalProperties": false
      },
      "SavedDto": {
        "type": "object",
        "properties": {
          "userID": {
            "type": "integer",
            "format": "int32"
          },
          "newsID": {
            "type": "integer",
            "format": "int32"
          }
        },
        "additionalProperties": false
      },
      "UserDto": {
        "type": "object",
        "properties": {
          "email": {
            "type": "string",
            "nullable": true
          },
          "password": {
            "type": "string",
            "nullable": true
          }
        },
        "additionalProperties": false
      },
      "UserRegisterDto": {
        "type": "object",
        "properties": {
          "username": {
            "type": "string",
            "nullable": true
          },
          "password": {
            "type": "string",
            "nullable": true
          },
          "email": {
            "type": "string",
            "nullable": true
          },
          "fullname": {
            "type": "string",
            "nullable": true
          },
          "phonenumber": {
            "type": "string",
            "nullable": true
          },
          "birthday": {
            "type": "string",
            "format": "date-time",
            "nullable": true
          },
          "avatar": {
            "type": "string",
            "nullable": true
          }
        },
        "additionalProperties": false
      }
    },
    "securitySchemes": {
      "Bearer": {
        "type": "http",
        "description": "Please enter into field the word 'Bearer' following by space and JWT",
        "scheme": "Bearer",
        "bearerFormat": "JWT"
      }
    }
  },
  "security": [
    {
      "Bearer": [ ]
    }
  ]
}